youtubedown/__init__.py
youtubedown/downloader.py
youtubedown/module1.py
youtubedown-1.0.8.dist-info/LICENSE
youtubedown-1.0.8.dist-info/METADATA
youtubedown-1.0.8.dist-info/WHEEL
youtubedown-1.0.8.dist-info/top_level.txt
youtubedown-1.0.8.dist-info/RECORD
