Metadata-Version: 2.1
Name: youtubedown
Version: 1.0.8
Summary: Allows you to asynchronously download Youtube_dl.
Home-page: https://github.com/8954sood/youtubedown
Author: babihoba
Author-email: hobabot@gmail.com
License: MIT
Platform: UNKNOWN
Classifier: Programming Language :: Python :: 3.8
Classifier: License :: OSI Approved :: MIT License
Classifier: Operating System :: OS Independent
Requires-Dist: youtube-dl (==2021.06.06)
